backtester272/.DS_Store
backtester272/Backtester.py
backtester272/DataBase.py
backtester272/Result.py
backtester272/Strategy.py
backtester272/StrategyBank.py
backtester272/Universe.py
backtester272/__init__.py
backtester272-1.0.2.dist-info/METADATA
backtester272-1.0.2.dist-info/WHEEL
backtester272-1.0.2.dist-info/RECORD
