Metadata-Version: 2.1
Name: backtester272
Version: 1.0.2
Summary: A backtesting project where you can also request binance and yfinance assets, and customize your strategies
Author: Jules MOURGUES-HAROCHE
Author-email: julesmourgues@gmail.com
Requires-Python: >=3.10,<4.0
Classifier: Programming Language :: Python :: 3
Classifier: Programming Language :: Python :: 3.10
Classifier: Programming Language :: Python :: 3.11
Classifier: Programming Language :: Python :: 3.12
Classifier: Programming Language :: Python :: 3.13
Requires-Dist: binance (>=0.3,<0.4)
Requires-Dist: matplotlib (>=3.9.3,<4.0.0)
Requires-Dist: nbformat (>=5.10.4,<6.0.0)
Requires-Dist: numpy (==1.26.4)
Requires-Dist: pandas (>=2.2.3,<3.0.0)
Requires-Dist: plotly (>=5.24.1,<6.0.0)
Requires-Dist: python-binance (>=1.0.25,<2.0.0)
Requires-Dist: scipy (>=1.14.1,<2.0.0)
Requires-Dist: seaborn (>=0.13.2,<0.14.0)
Requires-Dist: tabulate (>=0.9.0,<0.10.0)
Requires-Dist: yfinance (>=0.2.50,<0.3.0)
